Workbook

Sheet Inputs
A1: Student Cash CTD to Futures Basis Model
A3: Futures Price (decimal) | B3: 110.5 | L3: How to use
A4: Discount / financing rate | B4: 0.0525 | L4: 1 | M4: Enter futures price as decimal | N4: Example: 110.50
A5: Projection days | B5: 30 | L5: 2 | M5: Enter discount/financing rate | N5: Example: 5.25%
A6: Day step | B6: 5 | L6: 3 | M6: Change/add CTD rows | N6: Copy formulas in I:J if adding rows
A7: Selected CTD row | B7: 1 | L7: 4 | M7: Chart updates from projection sheet | N7: Shows basis in points
A8: Notes | B8: Input prices as decimal points per $100 not 32nds.
A10: CTD # | B10: CUSIP | C10: Maturity | D10: Coupon | E10: Clean Cash Price | F10: Accrued Interest | G10: Dirty Cash Price | H10: Conversion Factor | I10: Current Basis | J10: Current Basis / 32nds
A11: 1 | B11: 91282CJZ5 | C11: 48806 | D11: 0.03875 | E11: 99.8125 | F11: 0.682 | G11: 100.4945 | H11: 0.8276 | I11: =G11-($B$3*H11) -> 9.0447 | J11: =I11*32 -> 289.4304
A12: 2 | B12: 91282CKH3 | C12: 48990 | D12: 0.04 | E12: 100.21875 | F12: 0.411 | G12: 100.62975 | H12: 0.8351 | I12: =G12-($B$3*H12) -> 8.3512 | J12: =I12*32 -> 267.2384
A13: 3 | B13: 91282CKP5 | C13: 49171 | D13: 0.04125 | E13: 100.90625 | F13: 0.205 | G13: 101.11125 | H13: 0.8428 | I13: =G13-($B$3*H13) -> 7.98185 | J13: =I13*32 -> 255.4192
A14: 4 | B14: 91282CLD9 | C14: 49355 | D14: 0.0425 | E14: 101.40625 | F14: 0.073 | G14: 101.47925 | H14: 0.8504 | I14: =G14-($B$3*H14) -> 7.51005 | J14: =I14*32 -> 240.3216
A15: 5 | B15: 91282CLT3 | C15: 49536 | D15: 0.04375 | E15: 101.9375 | F15: 0.028 | G15: 101.9655 | H15: 0.8582 | I15: =G15-($B$3*H15) -> 7.1344 | J15: =I15*32 -> 228.3008

Sheet Basis Projection
A1: Projected Cash UST to Futures Basis
A3: Day | B3: Years | C3: CTD 1 Basis | D3: CTD 2 Basis | E3: CTD 3 Basis | F3: CTD 4 Basis | G3: CTD 5 Basis | I3: Summary | J3: Value
A4: 0 | B4: 0 | C4: =Inputs!G11*(1+Inputs!$B$4*$B4)-(Inputs!$B$3*Inputs!H11) -> 9.0447 | D4: =Inputs!G12*(1+Inputs!$B$4*$B4)-(Inputs!$B$3*Inputs!H12) -> 8.3512 | E4: =Inputs!G13*(1+Inputs!$B$4*$B4)-(Inputs!$B$3*Inputs!H13) -> 7.98185 | F4: =Inputs!G14*(1+Inputs!$B$4*$B4)-(Inputs!$B$3*Inputs!H14) -> 7.51005 | G4: =Inputs!G15*(1+Inputs!$B$4*$B4)-(Inputs!$B$3*Inputs!H15) -> 7.1344 | I4: Lowest current basis CTD | J4: =INDEX(Inputs!B11:B15,MATCH(MIN(Inputs!I11:I15),Inputs!I11:I15,0)) -> 91282CLT3
A5: 5 | B5: 0.013888889 | C5: =Inputs!G11*(1+Inputs!$B$4*$B5)-(Inputs!$B$3*Inputs!H11) -> 9.1179772 | D5: =Inputs!G12*(1+Inputs!$B$4*$B5)-(Inputs!$B$3*Inputs!H12) -> 8.4245759 | E5: =Inputs!G13*(1+Inputs!$B$4*$B5)-(Inputs!$B$3*Inputs!H13) -> 8.055577 | F5: =Inputs!G14*(1+Inputs!$B$4*$B5)-(Inputs!$B$3*Inputs!H14) -> 7.5840453 | G5: =Inputs!G15*(1+Inputs!$B$4*$B5)-(Inputs!$B$3*Inputs!H15) -> 7.2087498 | I5: Highest current basis CTD | J5: =INDEX(Inputs!B11:B15,MATCH(MAX(Inputs!I11:I15),Inputs!I11:I15,0)) -> 91282CJZ5
A6: 10 | B6: 0.027777778 | C6: =Inputs!G11*(1+Inputs!$B$4*$B6)-(Inputs!$B$3*Inputs!H11) -> 9.1912545 | D6: =Inputs!G12*(1+Inputs!$B$4*$B6)-(Inputs!$B$3*Inputs!H12) -> 8.4979517 | E6: =Inputs!G13*(1+Inputs!$B$4*$B6)-(Inputs!$B$3*Inputs!H13) -> 8.1293039 | F6: =Inputs!G14*(1+Inputs!$B$4*$B6)-(Inputs!$B$3*Inputs!H14) -> 7.6580406 | G6: =Inputs!G15*(1+Inputs!$B$4*$B6)-(Inputs!$B$3*Inputs!H15) -> 7.2830997 | I6: Selected CTD current basis | J6: =INDEX(Inputs!I11:I15,Inputs!B7) -> 9.0447
A7: 15 | B7: 0.041666667 | C7: =Inputs!G11*(1+Inputs!$B$4*$B7)-(Inputs!$B$3*Inputs!H11) -> 9.2645317 | D7: =Inputs!G12*(1+Inputs!$B$4*$B7)-(Inputs!$B$3*Inputs!H12) -> 8.5713276 | E7: =Inputs!G13*(1+Inputs!$B$4*$B7)-(Inputs!$B$3*Inputs!H13) -> 8.2030309 | F7: =Inputs!G14*(1+Inputs!$B$4*$B7)-(Inputs!$B$3*Inputs!H14) -> 7.7320359 | G7: =Inputs!G15*(1+Inputs!$B$4*$B7)-(Inputs!$B$3*Inputs!H15) -> 7.3574495 | I7: Selected CTD projected basis at final day | J7: =INDEX(C10:G10,1,Inputs!B7) -> 9.4843634
A8: 20 | B8: 0.055555556 | C8: =Inputs!G11*(1+Inputs!$B$4*$B8)-(Inputs!$B$3*Inputs!H11) -> 9.337809 | D8: =Inputs!G12*(1+Inputs!$B$4*$B8)-(Inputs!$B$3*Inputs!H12) -> 8.6447034 | E8: =Inputs!G13*(1+Inputs!$B$4*$B8)-(Inputs!$B$3*Inputs!H13) -> 8.2767578 | F8: =Inputs!G14*(1+Inputs!$B$4*$B8)-(Inputs!$B$3*Inputs!H14) -> 7.8060311 | G8: =Inputs!G15*(1+Inputs!$B$4*$B8)-(Inputs!$B$3*Inputs!H15) -> 7.4317994
A9: 25 | B9: 0.069444444 | C9: =Inputs!G11*(1+Inputs!$B$4*$B9)-(Inputs!$B$3*Inputs!H11) -> 9.4110862 | D9: =Inputs!G12*(1+Inputs!$B$4*$B9)-(Inputs!$B$3*Inputs!H12) -> 8.7180793 | E9: =Inputs!G13*(1+Inputs!$B$4*$B9)-(Inputs!$B$3*Inputs!H13) -> 8.3504848 | F9: =Inputs!G14*(1+Inputs!$B$4*$B9)-(Inputs!$B$3*Inputs!H14) -> 7.8800264 | G9: =Inputs!G15*(1+Inputs!$B$4*$B9)-(Inputs!$B$3*Inputs!H15) -> 7.5061492
A10: 30 | B10: 0.083333333 | C10: =Inputs!G11*(1+Inputs!$B$4*$B10)-(Inputs!$B$3*Inputs!H11) -> 9.4843634 | D10: =Inputs!G12*(1+Inputs!$B$4*$B10)-(Inputs!$B$3*Inputs!H12) -> 8.7914552 | E10: =Inputs!G13*(1+Inputs!$B$4*$B10)-(Inputs!$B$3*Inputs!H13) -> 8.4242117 | F10: =Inputs!G14*(1+Inputs!$B$4*$B10)-(Inputs!$B$3*Inputs!H14) -> 7.9540217 | G10: =Inputs!G15*(1+Inputs!$B$4*$B10)-(Inputs!$B$3*Inputs!H15) -> 7.5804991
